dnp3/__init__.py
dnp3/py.typed
dnp3/application/__init__.py
dnp3/application/builder.py
dnp3/application/fragment.py
dnp3/application/header.py
dnp3/application/parser.py
dnp3/application/qualifiers.py
dnp3/core/__init__.py
dnp3/core/crc.py
dnp3/core/enums.py
dnp3/core/exceptions.py
dnp3/core/flags.py
dnp3/core/timestamp.py
dnp3/core/types.py
dnp3/database/__init__.py
dnp3/database/database.py
dnp3/database/event_buffer.py
dnp3/database/point.py
dnp3/datalink/__init__.py
dnp3/datalink/builder.py
dnp3/datalink/control.py
dnp3/datalink/frame.py
dnp3/datalink/parser.py
dnp3/master/__init__.py
dnp3/master/commands.py
dnp3/master/config.py
dnp3/master/handler.py
dnp3/master/master.py
dnp3/master/polling.py
dnp3/master/state.py
dnp3/objects/__init__.py
dnp3/objects/analog_input.py
dnp3/objects/base.py
dnp3/objects/binary_input.py
dnp3/objects/binary_output.py
dnp3/objects/class_data.py
dnp3/objects/counter.py
dnp3/objects/registry.py
dnp3/objects/time.py
dnp3/outstation/__init__.py
dnp3/outstation/config.py
dnp3/outstation/handler.py
dnp3/outstation/outstation.py
dnp3/outstation/state.py
dnp3/transport/__init__.py
dnp3/transport/reassembler.py
dnp3/transport/segment.py
dnp3/transport/segmenter.py
dnp3/transport_io/__init__.py
dnp3/transport_io/channel.py
dnp3/transport_io/simulator.py
dnp3/transport_io/tcp_client.py
dnp3/transport_io/tcp_server.py
dnp3py-0.1.0.dist-info/METADATA
dnp3py-0.1.0.dist-info/WHEEL
dnp3py-0.1.0.dist-info/licenses/LICENSE
dnp3py-0.1.0.dist-info/RECORD
